Workbook

Sheet 0_README
A1: 淘天集团 FY25 BP分析过程工作簿
A2: 时间口径：阿里 FY25（2024.4–2025.3） | 编制：王静 Jennie | 日期：2026.05 | v2.0
A4: 目的 | B4: 为同名 Word 分析报告提供所有计算明细、可追溯口径、可调参数。Word 与 Excel 数字完全一致；如有不一致以本工作簿为准。
A6: 颜色约定（必读）
B7: 浅蓝底 = 输入/假设单元格（可修改测试敏感性）
B8: 浅绿底 = 计算结果（公式自动生成）
B9: 浅黄底 = 关键 BP 监控指标
A10: 🔴 | B10: 红字 = 警示性数据 / 口径备注
A12: 数据可信度图例
A13: ● | B13: 官方披露口径（来自年报/季报/SEC文件）
A14: ⚠ | B14: 估算（带敏感性区间，详见 8_口径与假设）
A16: 工作表清单（按 BP 分析流程编排）
A17: 1_市场份额测算 | B17: 对应 Word 第 1 章 — 行业大盘与三家份额
A18: 2_收入结构拆解 | B18: 对应 Word 第 2 章 — 淘天 FY23-25 收入与利润结构
A19: 3_PL_Bridge | B19: 对应 Word 第 3 章 — FY25 CMR +75 亿归因（5 维度）
A20: 4_UE单位经济模型 | B20: 对应 Word 第 4 章 — 三视角 UE
A21: 5_驱动因子树 | B21: 对应 Word 第 5 章 — Driver Tree 三层穿透
A22: 6_同业对标 | B22: 对应 Word 第 6 章 — 三家可比口径 + 战略象限
A23: 7_敏感性与情景 | B23: 对应 Word 第 7 章 — FY26 五情景 + 弹性矩阵
A24: 8_问题诊断与建议 | B24: 对应 Word 第 8、9 章 — 5 大问题 + 12 KPI
A25: 9_口径与假设 | B25: 附录 A — 所有口径声明
A26: 10_数据源链接 | B26: 附录 B — 每项数据的官方/研报来源

Sheet 1_市场份额测算
A1: 中国电商市场总览与三家份额
A2: 口径：实物商品网络零售额（国家统计局）+ 服务类按行业研报估算 | 时间：日历年 2022–2024
A4: 指标 | B4: 2022 | C4: 2023 | D4: 2024 | E4: YoY 2024 | F4: 数据来源 / 备注
A5: 【行业大盘】
A6: 全国实物网零额（万亿） | B6: 11.96 | C6: 13.02 | D6: 13.79 | E6: +5.9% | F6: ● 国家统计局 2024.12
A7: 全国社零总额（万亿） | B7: 43.97 | C7: 47.15 | D7: 48.79 | E7: +3.5% | F7: ● 国家统计局
A8: 网零渗透率% | B8: 27.2 | C8: 27.6 | D8: 28.3 | E8: +0.7pct | F8: ● 网零/社零，电商成熟度
A9: 含服务广义电商（万亿） | B9: 14.5 | C9: 15.8 | D9: 16.8 | E9: +6.3% | F9: ⚠ 加 O2O+本地生活
A10: 【三家 GMV 与市占率】
A11: 淘天 GMV（万亿） | B11: 8 | C11: 7.8 | D11: 7.6 | E11: -2.6% | F11: ● FY23/24/25 ≈ CY22/23/24 | G11: 券商机构主流测算
A12: 淘天市占率% | B12: 55.2 | C12: 49.4 | D12: 45.2 | E12: -4.2pct | F12: ⚠ 淘天 GMV / 广义电商
A13: PDD 主站 GMV（万亿） | B13: 2.8 | C13: 4.1 | D13: 5.3 | E13: +29% | F13: ⚠ 区间 5.0–5.6（中位 5.3）
A14: PDD 市占率% | B14: 19.3 | C14: 25.9 | D14: 31.5 | E14: +5.6pct | F14: ⚠ 增速最快
A15: JD 零售 GMV（万亿） | B15: 2.85 | C15: 2.9 | D15: 3.05 | E15: +5.2% | F15: ⚠ JD 不再披露 GMV
A16: JD 市占率% | B16: 19.7 | C16: 18.4 | D16: 18.2 | E16: -0.2pct | F16: ⚠ 基本盘稳定
A17: 抖音电商 GMV（万亿） | B17: 1.4 | C17: 2.2 | D17: 3.5 | E17: +59% | F17: ⚠ 区间 3.0–3.7
A18: 抖音市占率% | B18: 9.7 | C18: 13.9 | D18: 20.8 | E18: +6.9pct | F18: ⚠ 最大新进入者
A19: 【份额合计校验】
A20: CR4 合计% | B20: 103.9 | C20: 107.6 | D20: 115.7 | E20: — | F20: >100% 因部分 GMV 重复计入（品牌商多渠道）
A22: 💡 BP 行业判断：电商"双寡头时代"已结束，进入"四足鼎立 + 长尾"。淘天份额从 2022 年 55% 降至 2024 年 45%，三年损失 10pct。BP 真问题不是"淘天会不会输"，而是"能否守住 40% 份额底线 + 47% 利润率底线"。

Sheet 2_收入结构拆解
A1: 淘天集团收入结构（FY23–FY25）
A2: 口径：阿里财年 FY23/24/25 = 2022.4–2025.3 | 单位：亿元
A4: 科目 | B4: FY23 | C4: FY24 | D4: FY25 | E4: CAGR | F4: YoY 25 | G4: BP 视角
A5: 【收入科目（亿元）】
A6: 中国零售商业 | B6: =B7+B10 | C6: =C7+C10 | D6: =D7+D10 | E6: =(D6/B6)^(1/2)-1 | F6: =(D6-C6)/C6
A7: 客户管理收入 CMR ● | B7: 2915 | C7: 3040 | D7: 3223 | E7: =(D7/B7)^(1/2)-1 | F7: =(D7-C7)/C7 | G7: 广告+佣金，最重要科目
A8: 广告收入（72、68、64%估）⚠ | B8: =B7*0.72 | C8: =C7*0.68 | D8: =D7*0.64 | E8: =(D8/B8)^(1/2)-1 | F8: =(D8-C8)/C8 | G8: 三年比例逐年下降，数据来源：豆包
A9: 佣金收入（28、32、36%估）⚠ | B9: =B7-B8 | C9: =C7-C8 | D9: =D7-D8 | E9: =(D9/B9)^(1/2)-1 | F9: =(D9-C9)/C9 | G9: 平台新增订单服务费、天猫部分类目佣金上调、全站推广小幅分流广告结构。
A10: 直营业务收入 ● | B10: 1038 | C10: 1104 | D10: 1032 | E10: =(D10/B10)^(1/2)-1 | F10: =(D10-C10)/C10 | G10: FY25 主动收缩
A11: 中国批发商业 | B11: 178 | C11: 205 | D11: 243 | E11: =(D11/B11)^(1/2)-1 | F11: =(D11-C11)/C11
A13: 分部收入合计 ● | B13: =B6+B11 | C13: =C6+C11 | D13: =D6+D11 | E13: =(D13/B13)^(1/2)-1 | F13: =(D13-C13)/C13 | G13: 增长放缓
A14: 同期 GMV（亿元）● | B14: ='1_市场份额测算'!B11*10000 | C14: ='1_市场份额测算'!C11*10000 | D14: ='1_市场份额测算'!D11*10000 | E14: =(D14/B14)^(1/2)-1 | F14: =(D14-C14)/C14 | G14: 连续下滑两年
A15: 【变现率（计算列：浅绿底）】
A16: 综合 Take Rate%（=收入/GMV） | B16: =B13/B14*100 | C16: =C13/C14*100 | D16: =D13/D14*100 | E16: =(D16/B16)^(1/2)-1 | F16: =(D16-C16)/C16 | G16: GMV 降但变现率升
A17: CMR Take Rate%（=CMR/GMV） | B17: =B7/B14*100 | C17: =C7/C14*100 | D17: =D7/D14*100 | E17: =(D17/B17)^(1/2)-1 | F17: =(D17-C17)/C17 | G17: 核心观察指标
A18: 【盈利结构】
A19: 分部经营利润 ● | B19: 1891 | C19: 1948 | D19: 1962 | E19: =(D19/B19)^(1/2)-1 | F19: =(D19-C19)/C19 | G19: —
A20: 分部经营利润率% | B20: =B19/B13*100 | C20: =C19/C13*100 | D20: =D19/D13*100 | E20: =(D20/B20)^(1/2)-1 | F20: =(D20-C20)/C20 | G20: 持续下降
A23: 【FY25 收入变动归因（衔接 Sheet 3 P&L Bridge）】
A24: CMR 增量 | B24: 91 | C24: Take Rate +0.20pct
A25: └ 广告增量 | B25: =B24 | C25: Take Rate 提升驱动
A26: └ 佣金增量 | B26: 0 | C26: 基本持平
A27: 直营增量 | B27: -81 | C27: FY25 主动收缩猫超长尾
A28: 合计变动 | B28: -6 | C28: 对应 -0.1% YoY
A30: 分析：FY25 收入增长放缓（Y to Y2025=+3.4%，CAGR=4.3%），但内部结构显著优化：CMR（高毛利）继续 +8.8%（CAGR=7.9%），直营（低毛利甚至亏损）-6.5%。这是典型的"主动收缩长尾"动作。 问题：当 GMV 已经 -2.6%，CMR 继续上还要靠 Take Rate 拉，触顶临近。

Sheet 3_PL_Bridge
A1: FY25 CMR 同比 +183 亿元 P&L Bridge
A2: 维度：价、量、结构、会员、基数 | 目标：归因误差 ≤ 5%（±3.75 亿）
A4: 归因项 | B4: 影响（亿元） | C4: 类型 | D4: 计算逻辑 | E4: 依据
A5: FY24 CMR 起点 | B5: ='2_收入结构拆解'!C7 | C5: 锚点 | D5: — | E5: FY24 实际值
A6: 价：佣金率结构提升 (1.25%→1.53%, +0.28pct) | B6: 213 | C6: + 顺风 | D6: 0.28% × 76000亿 GMV | E6: 佣金率结构性上行（订单服务费+类目佣金调整）
A7: 价：广告变现率微降 (2.65%→2.71%, +0.06pct) | B7: -4 | C7: − 逆风 | D7: 广告收入 2067→2063亿，绝对值下降 | E7: 广告流量增速放缓 + 全站推产品分流
A8: 量：GMV -2.6% (7.8→7.6万亿) | B8: -78 | C8: − 逆风 | D8: (7.6-7.8)万亿 × FY24 Take Rate 3.90% | E8: 用户基本盘 + 客单价双重承压
A9: 结构 + 会员：高客单类目 + 88VIP 增量 | B9: 69 | C9: + 顺风 | D9: 类目溢价 +24 / 88VIP +45 | E9: 88VIP +1500万 × 频次效应
A10: 基数：FY24 直播一次性高基不复现 | B10: -17 | C10: − 逆风 | D10: FY24 双 11 直播单场亿级 FY25 未复现 | E10: 公开市场跟踪
A11: FY25 CMR 实际 | B11: 3223 | C11: 锚点 | D11: — | E11: FY25 实际值
A13: 【归因校验】
A14: 归因合计 | B14: =SUM(B6:B10) | C14: =合计 | D14: 5 个归因项加总 | E14: 应等于实际变动
A15: 实际变动 | B15: =B11-B5 | C15: =FY25 - FY24 | D15: 3,132 - 3,057 | E15: 3,223 - 3,040
A16: 归因误差 | B16: =ABS(B14-B15)/B15 | C16: 误差% | D16: 目标 ≤ 5% | E16: 0% 完美归因 ✓
A18: 💡 BP 解读：FY25 CMR +183 亿的核心驱动是"佣金率结构性提升" (+213亿) ——新增订单服务费、天猫类目佣金调整带动佣金占比从 28% 升至 36%。这是阿里变现模式的结构性切换：从"广告主导"向"佣金+广告"双轮转。但代价是分部经营利润率从 45.8% 降至 43.6%（下降 2.2pct）—— 佣金虽收入贡献大，但毛利率低于广告，结构变化压制了利润率。

Sheet 4_UE单位经济模型
A1: 淘天 UE 单位经济模型
A2: 三视角：每位活跃买家 / 每元 CMR / 每笔订单 | 口径：FY23-FY25
A4: 指标 | B4: FY23 | C4: FY24 | D4: FY25 | E4: 解读
A5: 【视角 A：每位活跃买家（人均经济）】 | H5: AAC的数据来源
A6: 年活跃买家 AAC（亿）⚠ | B6: 10.3 | C6: 10 | D6: 9.5 | E6: 三年 -0.8 亿，估算口径
A7: 每买家年 GMV（元） | B7: ='2_收入结构拆解'!B14/'4_UE单位经济模型'!B6 | C7: ='2_收入结构拆解'!C14/'4_UE单位经济模型'!C6 | D7: ='2_收入结构拆解'!D14/'4_UE单位经济模型'!D6 | E7: 钱包深度小幅提升
A8: 每买家分部收入（元） | B8: ='2_收入结构拆解'!B13/'4_UE单位经济模型'!B6 | C8: ='2_收入结构拆解'!C13/'4_UE单位经济模型'!C6 | D8: ='2_收入结构拆解'!D13/'4_UE单位经济模型'!D6 | E8: 变现效率提升
A9: 每买家 CMR（元）⭐ | B9: ='2_收入结构拆解'!B7/'4_UE单位经济模型'!B6 | C9: ='2_收入结构拆解'!C7/'4_UE单位经济模型'!C6 | D9: ='2_收入结构拆解'!D7/'4_UE单位经济模型'!D6 | E9: BP 最纯指标
A10: 每买家分部利润（元） | B10: ='2_收入结构拆解'!B19/'4_UE单位经济模型'!B6 | C10: ='2_收入结构拆解'!C19/'4_UE单位经济模型'!C6 | D10: ='2_收入结构拆解'!D19/'4_UE单位经济模型'!D6 | E10: UE 底线持续向好
A11: 【视角 B：每元 CMR 成本结构（估算）】
A12: CMR 收入 | B12: 1.00 | C12: 1.00 | D12: 1.00 | E12: 基准
A13: − 流量获取成本 | B13: -0.08 | C13: -0.07 | D13: -0.07 | E13: 搜索/推荐分发成本
A14: − 商家运营/客服 | B14: -0.05 | C14: -0.05 | D14: -0.05 | E14: —
A15: − 技术/IT 分摊 | B15: -0.04 | C15: -0.04 | D15: -0.04 | E15: —
A16: − 营销与品牌 | B16: -0.10 | C16: -0.09 | D16: -0.08 | E16: 含天猫双 11 品牌投放
A17: − 研发分摊 | B17: -0.04 | C17: -0.04 | D17: -0.04 | E17: 研发费用按收入比例分摊
A18: − 管理与其他 | B18: -0.03 | C18: -0.03 | D18: -0.03 | E18: —
A19: 每元 CMR 经营利润 ⭐ | B19: 0.66 | C19: 0.68 | D19: 0.69 | E19: 高毛利广告业务的真实经济模型
A20: 【视角 C：每笔订单】
A21: 年订单数（亿单）⚠ | B21: 927 | C21: 1000 | D21: 997 | E21: AAC × 频次反推
A22: 客单价 AOV（元） | B22: 86 | C22: 78 | D22: 76 | E22: 消费降级 + 高频低价化
A23: CMR/单（元） | B23: 3.16 | C23: 3.06 | D23: 3.14 | E23: 单笔抽水基本稳
A25: 💡 UE 三视角综合：FY25 每买家 CMR 339 元（CMR 3223亿 / AAC 9.5亿）—— 三年从 283 涨到 339（+20%）。但每买家分部利润仅 207 元（FY23 184），说明变现效率上升的同时，单位利润提升幅度有限——佣金为主的变现模型相比广告需要更多运营投入，反映在利润率持续下降上。

Sheet 5_驱动因子树
A1: Driver Tree 三层穿透
A2: 公式：CMR = AAC × 每买家GMV × Take Rate；Take Rate = 广告变现率 + 佣金率
A4: 层级 | B4: 驱动因子 | C4: FY23 | D4: FY24 | E4: FY25 | F4: FY25-FY23 / 解读
A5: 【一级因子：CMR = AAC × 每买家GMV × Take Rate】
A6: L1 | B6: AAC（亿）⚠ | C6: 10.3 | D6: 10 | E6: 9.5 | F6: −0.8 ⇩ 拖累
A7: L1 | B7: 每买家 GMV（元） | C7: 7767 | D7: 7800 | E7: 8000 | F7: +233 ⇧ 提升
A8: L1 | B8: CMR Take Rate% ⭐ | C8: 3.64 | D8: 3.9 | E8: 4.24 | F8: +0.60pct ⇧ 提升（佣金率拉动为主）
B9: 推算 CMR（亿）= 公式 | C9: =C6*C7*C8/100 | D9: =D6*D7*D8/100 | E9: =E6*E7*E8/100 | F9: 公式自动算
A10: 【二级因子：Take Rate 拆分（广告 + 佣金）】
A11: L2 | B11: 广告变现率 % | C11: 2.62 | D11: 2.65 | E11: 2.71 | F11: +0.09pct ⇧ 微涨（绝对额下降）
A12: L2 | B12: 佣金率 % | C12: 1.02 | D12: 1.25 | E12: 1.53 | F12: +0.51pct ⇧⇧ 主导驱动（结构性切换）
B13: 合计 Take Rate %（=广告+佣金） | C13: =C11+C12 | D13: =D11+D12 | E13: =E11+E12 | F13: 应等于 4.12% ✓
A14: 【三级因子：广告变现率 = 投放渗透率 × 平均投放 × 转化率指数】
A15: L3 | B15: (广告维度) 商家投放渗透率% ⚠ | C15: 35 | D15: 38 | E15: 42 | F15: +7pct ⇧ 中小商家投放扩面
A16: L3 | B16: (广告维度) 平均投放（万元/商家）⚠ | C16: 28 | D16: 30 | E16: 31 | F16: +3 ⇧ ROI 改善带动加投
A17: L3 | B17: (佣金维度) 类目佣金率提升 + 订单服务费 ⚠ | C17: — | D17: +5% | E17: +12% | F17: FY25 大幅提升（天猫部分类目+全站推产品）
A19: 💡 Driver Tree 总结：FY25 Take Rate +0.60pct 的真正驱动不是"广告越收越多"，而是"佣金率结构性切换"——佣金率三年从 1.02% 升到 1.53% (+0.51pct)，贡献 Take Rate 增量的 85%。广告变现率相对平稳 (2.62→2.71%)。这说明阿里变现路径在转：广告天花板已现，转向更稳定的"GMV 抽佣"模式。

Sheet 6_同业对标
A1: 三家可比口径对标（已剔除 Temu / 物流 / 海外）
A2: 口径：FY25 ≈ CY2024
A4: 指标 | B4: 淘天 | C4: PDD 主站 | D4: JD 零售 | E4: BP 洞察
A5: 【规模】
A6: GMV(万亿) | B6: 7.6 | C6: 5.3 | D6: 3.05 | E6: 淘天 >> PDD >> JD
A7: GMV YoY% | B7: -2.6 | C7: 29 | D7: 5.2 | E7: 淘天 GMV 仍下降，但收入侧通过佣金率切换实现 +3.4% 增长
A8: 市占率% | B8: 45.2 | C8: 31.5 | D8: 18.2 | E8: 差距三年从 35pct 缩到 14pct
A9: 【变现能力】
A10: 分部收入(亿) | B10: 4498 | C10: 2750 | D10: 10037 | E10: JD 自营口径不可比
A11: 综合TakeRate% | B11: 5.92 | C11: 5.19 | D11: — | E11: 淘天领先 0.54pct
A12: CMR_TakeRate% | B12: 4.24 | C12: 3.74 | D12: — | E12: ⭐ 淘天广告效率仍最高
A13: 【盈利效率】
A14: 经营利润(亿) | B14: 1962 | C14: 900 | D14: 447 | E14: —
A15: 经营利润率% | B15: 43.62 | C15: 32.7 | D15: 4.5 | E15: 淘天利润率最高，但 FY25 已开始结构性下降（45.8→43.6%）
A16: 每买家分部利润(元) | B16: 206 | C16: 92 | D16: 73 | E16: ⭐ 淘天单买家盈利仍是 PDD 的 2.2 倍（206 vs 92），但优势在收窄
A17: 【用户经济】
A18: AAC(亿) | B18: 9.5 | C18: 9.8 | D18: 6.1 | E18: PDD 用户已超淘天
A19: 买家年GMV(元) | B19: 8000 | C19: 5408 | D19: 5000 | E19: 淘天钱包深度仍领先
A20: 客单价AOV(元) | B20: 76 | C20: 69 | D20: 3800 | E20: JD 3C 高客单
A21: 年下单频次 | B21: 105 | C21: 78 | D21: 50 | E21: 淘天频次最高
A23: 💡 对标三结论：① 体量上淘天仍是规模王，但 GMV 已 -2.6% 与 PDD +29% 形成强烈反差；② 变现率上淘天 5.92% 仍领先 PDD 5.19%，但领先优势主要靠佣金率（不是广告）；③ 淘天经营利润率 43.6% 已三年连降，PDD 的 32.7% 仍在上升——长期看两者会收敛。

Sheet 7_敏感性与情景
A1: FY26 CMR 五情景预测 + 弹性矩阵
A2: 可修改浅蓝输入区，浅绿区自动重算 | 起点：FY25 AAC=9.5亿、每买家GMV=8000元、CMR=3132亿
A4: 情景 | B4: AAC YoY% | C4: 每买家GMV YoY% | D4: Take Rate % | E4: 推算 AAC（亿） | F4: 推算 GMV（万亿） | G4: 推算 CMR（亿） | H4: CMR YoY%
A5: 【输入区（浅蓝可修改）】 + 【计算区（浅绿自动）】
A6: 极悲观 | B6: -10 | C6: -5 | D6: 3.95 | E6: =9.5*(1+B6/100) | F6: =E6*8000*(1+C6/100)/10000 | G6: =F6*10000*D6/100 | H6: =(G6-3223)/3223*100
A7: 悲观 | B7: -8 | C7: -3 | D7: 4.05 | E7: =9.5*(1+B7/100) | F7: =E7*8000*(1+C7/100)/10000 | G7: =F7*10000*D7/100 | H7: =(G7-3223)/3223*100
A8: 基准 | B8: -3 | C8: 2 | D8: 4.2 | E8: =9.5*(1+B8/100) | F8: =E8*8000*(1+C8/100)/10000 | G8: =F8*10000*D8/100 | H8: =(G8-3223)/3223*100
A9: 乐观 | B9: 0 | C9: 5 | D9: 4.3 | E9: =9.5*(1+B9/100) | F9: =E9*8000*(1+C9/100)/10000 | G9: =F9*10000*D9/100 | H9: =(G9-3223)/3223*100
A10: 极乐观 | B10: 3 | C10: 8 | D10: 4.4 | E10: =9.5*(1+B10/100) | F10: =E10*8000*(1+C10/100)/10000 | G10: =F10*10000*D10/100 | H10: =(G10-3223)/3223*100
A12: 【弹性矩阵：每变 +1pct 对 FY26 CMR 影响】
A13: 变量 | B13: +1pct CMR 影响（亿） | C13: % of FY25 CMR | D13: BP 监控权重
A14: AAC YoY +1pct | B14: 31 | C14: 0.01 | D14: 高
A15: 每买家GMV YoY +1pct | B15: 31 | C15: 0.01 | D15: 高
A16: Take Rate +0.10pct | B16: 76 | C16: 0.024 | D16: 极高（已触顶）
A17: 88VIP数 +1000万 | B17: 57 | C17: 0.018 | D17: 中（执行难度大）
A19: 💡 BP 预算锚定建议：基于 FY25 CMR 3,223 亿基准，FY26 基准情景 CMR 约 3,400 亿（+5%），需要佣金率持续提升空间。悲观情景 -12% 时，重点是费用刚性管理：销售/研发费用率 -1pct/-0.5pct 预案。管理层警惕：FY25 利润率已下降 2.2pct，FY26 若 GMV 继续下行，利润率压力将加剧。

Sheet 8_问题诊断与建议
A1: 5 大问题诊断 + 量化 BP 建议 + 12 KPI
A2: BP 行动建议遵循"投入 / 回报 / 回收期 / 关键风险"四件套
A4: # | B4: 问题 | C4: 量化影响 | D4: 根因 | E4: 改进路径 | F4: 量化潜力 / 风险
A5: #1 | B5: AAC 流失 | C5: 每流失 1 亿 AAC ≈ -34 亿 CMR/年（按每买家 CMR 339 元） | D5: PDD低价心智+抖音内容流抢用户 | E5: 88VIP扩容 + 淘宝直播二次发力 | F5: AAC回到10亿 ≈ +5%CMR；风险：补贴成本上升
A6: #2 | B6: 直营业务亏损 | C6: FY25 利润率 43.6%，三年降 2.2pct，结构性侵蚀（非直营单一原因） | D6: 佣金占比上升压制毛利率（佣金毛利率低于广告） | E6: 广告产品创新+佣金分层定价 | F6: 防止利润率跌破 40%；风险：广告增量空间有限
A7: #3 | B7: 客单价下滑 | C7: AOV 86→76元，三年-12% | D7: 消费降级 + 品类结构 | E7: 推高客单类目（家电/美妆/3C）占比 | F7: AOV回升5% ≈ +5%GMV；风险：高客单类目竞争激烈
A8: #4 | B8: Take Rate 触顶 | C8: 4.24% 超 PDD 0.5pct，再上提风险加剧 | D8: 广告ROI已被中长尾商家抱怨 | E8: 不上提Take Rate，转向广告产品创新 | F8: +0.10pct ≈ +76亿CMR；风险：5-8% 商家流失对冲全部上行
A9: #5 | B9: 二曲线缺位 | C9: 直播+海外GMV占比<8% | D9: 资源投入分散 | E9: 聚焦淘宝直播 + 速卖通AE Choice | F9: 3年贡献GMV占比12%；风险：抖音/Temu竞争
A11: 【BP 量化行动建议（投入/回报/回收期/风险四件套）】
A12: 行动 | B12: 投入 | C12: 回报 | D12: 回收期 | E12: 关键风险
A13: 88VIP 扩 5000万 → 1亿 | B13: 会员费补贴+15亿/年；获客成本+8亿/年（合计23亿） | C13: GMV +480亿；CMR +20.4亿（按 4.24% Take Rate） | D13: ~1.5年 | E13: PDD百亿补贴每加码10亿，VIP流失约3pct
A14: 重新评估直营长尾 SKU | B14: 结构性收缩 -50 亿/年（对比 FY25 已主动收缩 -72 亿） | C14: 聚焦高频日百，提升单 SKU 利润率 | D14: ~2 年 | E14: 失去高频流量入口，影响 AAC 留存
A15: 防守 Take Rate 在4.10%-4.15%（不上提） | B15: 放弃理论+76亿CMR的上行 | C15: 避免商家流失（按 +0.10pct 触发 5-8% 流失，对应 -150~-240亿 GMV） | D15: — | E15: 商家承受度阈值实际可能更低
A16: 淘宝直播GMV占比 → 12% | B16: 内容补贴+25亿/年；主播激励+10亿/年（合计35亿） | C16: GMV +1,800亿；CMR +54亿（按 3.0% 直播 Take Rate） | D16: ~2.0年 | E16: 抖音电商挤压，主播迁移成本高
A18: 【12 项核心监控 KPI】
A19: # | B19: KPI | C19: 口径 | D19: 目标值 | E19: 预警阈值 | F19: 负责部门
A20: 1 | B20: GMV同比 | C20: 日历季度 | D20: +0%~+2% | E20: <-3% | F20: 电商BU
A21: 2 | B21: AAC同比 | C21: 滚动12月 | D21: 持平 | E21: <-3% | F21: 用户增长
A22: 3 | B22: 每买家CMR同比 | C22: 滚动12月 | D22: +5%~+8% | E22: <+3% | F22: 商业化
A23: 4 | B23: CMR同比 | C23: 日历季度 | D23: +5%~+8% | E23: <+3% | F23: 商业化
A24: 5 | B24: CMR Take Rate | C24: CMR/GMV | D24: +3%~+6% | E24: <+0% | F24: 商业化
A25: 6 | B25: 商家投放渗透率 | C25: 季度 | D25: 4.20%~4.30% | E25: <4.10% 或 >4.40% | F25: 商业化
A26: 7 | B26: 广告ROI(商家) | C26: 第三方监测 | D26: ≥7倍 | E26: <6倍 | F26: 商业化
A27: 8 | B27: 88VIP数 | C27: 月末时点 | D27: +10% | E27: <+5% | F27: 会员
A28: 9 | B28: 直播GMV占比 | C28: 季度 | D28: +2pct/年 | E28: <+1pct | F28: 内容
A29: 10 | B29: 分部经营利润率 | C29: 分部利润/收入 | D29: ≥43% | E29: <41% | F29: CFO+BP
A30: 11 | B30: 运营费用率 | C30: (销+管+研)/收入 | D30: ≤22% | E30: >24% | F30: CFO+BP
A31: 12 | B31: 自由现金流 | C31: 季度披露 | D31: >800亿/季 | E31: <700亿 | F31: 财务部

Sheet 9_口径与假设
A1: 口径声明 + 关键估算假设
A2: 本表是 Word 报告附录 A 的完整版
A4: 类别 | B4: 口径 / 假设 | C4: 依据 / 解释 | D4: 敏感性区间
A5: 时间口径 | B5: FY23/24/25 | C5: 阿里财年截至 3 月，FY25 = 2024.4–2025.3 | D5: —
A6: 货币 | B6: 人民币亿元 | C6: 所有金额若无特别说明均为 RMB 亿元 | D6: —
A7: 可比口径 | B7: 淘天 vs PDD主站 vs JD零售 | C7: 已剔除 Temu / 京东物流 / 海外 / 菜鸟 | D7: —
A8: 会计准则 | B8: IFRS（淘天/JD）；US GAAP（PDD） | C8: SBC 处理与租赁分类有差异，毛利口径基本一致 | D8: —
A9: 淘天 GMV ● | B9: 年报披露 | C9: 阿里 2022 起不单独披露季度 GMV，年度披露 | D9: —
A10: PDD 主站 GMV ⚠ | B10: 研报中位数 | C10: 高盛/中金/MS：2022 2.8 / 2023 4.1 / 2024 5.3 万亿 | D10: ±5%（5.0–5.6）
A11: JD 零售 GMV ⚠ | B11: 倒推估算 | C11: JD 2022 起不再披露，按 GMV/收入 ≈ 2.9 倒推 | D11: ±5%
A12: 淘天 AAC ⚠ | B12: 研报估算 | C12: 阿里 2022Q4 起不单独披露 AAC | D12: ±3%
A13: PDD 主站 AAC ⚠ | B13: 近似总 AAC | C13: Temu 不开账户，主站和 Temu 共用账户体系 | D13: —
A14: CMR 拆分 ⚠ | B14: 广告:佣金 = 72:28 → 68:32 → 64:36 | C14: FY23/24/25 比例逐年变化（用户更新数据） | D14: ±2%
A15: CMR Take Rate | B15: =CMR / GMV | C15: 最纯粹的"广告变现率" | D15: —
A16: 综合 Take Rate | B16: =分部收入 / GMV | C16: 含直营/广告/佣金 | D16: —
A17: CMR 利润率 ⚠ | B17: FY25 综合 43.6%（三年 -2.2pct） | C17: 佣金占比上升压制毛利率 | D17: ±1pct
A18: 直营利润率 ⚠ | B18: +2.5%~-2.2% | C18: 自营业务低毛利且 FY25 亏损 | D18: ±1pct
A19: FY26 基准情景 | B19: AAC YoY -3%, ARPU YoY +2%, Take Rate 4.20% | C19: 维持 FY25 趋势小幅放缓 | D19: 见 Sheet 7

Sheet 10_数据源链接
A1: 数据源 + 在哪一节查找
A2: 本表是 Word 报告附录 B 的完整版
A4: 类别 | B4: 来源 | C4: URL | D4: 查找路径
A5: 淘天财务 | B5: 阿里 IR 官网 | C5: https://www.alibabagroup.com/en-US/ir | D5: Reports → FY25 Annual Report
A6: 淘天分部 | B6: 港交所披露易（9988） | C6: https://www1.hkexnews.hk/ | D6: 搜 9988 → 2024/2025 年度业绩公告
A7: 淘天 KPI 电话会 | B7: 阿里 IR 官网 | C7: https://www.alibabagroup.com/en-US/ir | D7: Quarterly Results → Earnings
A8: 行业大盘 | B8: 国家统计局 | C8: http://www.stats.gov.cn/ | D8: 商品零售统计 → 网上零售额
A9: 行业大盘 | B9: 商务部电子商务研究中心 | C9: http://www.100ec.cn/ | D9: 电子商务发展报告
A10: 行业大盘 | B10: 艾瑞咨询 | C10: https://www.iresearch.com.cn/ | D10: 电商行业季报
A11: 行业大盘 | B11: QuestMobile | C11: https://www.questmobile.com.cn/ | D11: 移动互联网发展报告
A12: PDD 财务 | B12: PDD IR | C12: https://investor.pddholdings.com/ | D12: Financial Information
A13: PDD SEC | B13: EDGAR | C13: https://www.sec.gov/cgi-bin/browse-edgar | D13: 20-F
A14: PDD 主站估算 | B14: 券商研报 | C14: — | D14: 搜"拼多多 deep dive" - 慧博/远瞻
A15: JD 财务 | B15: 京东 IR | C15: https://ir.jd.com/ | D15: 财报 → 按分部经营
... A19: 综合 | B19: Macrotrends | C19: https://www.macrotrends.net/ | D19: 10 年财务数据
